[ {
  "id" : "60e818e0c1551b0f813ec8fb",
  "title" : "a",
  "description" : "a",
  "numResponses" : 1,
  "questions" : [ ],
  "formAnswers" : [ ],
  "study" : {
    "id" : "60e8136dc1551b0f813ec8f9",
    "title" : "Study1",
    "description" : "Lorem",
    "numParticipants" : 1,
    "numForms" : 2
  }
}, {
  "id" : "60e818e7c1551b0f813ec8fc",
  "title" : "b",
  "description" : "b",
  "numResponses" : 2,
  "questions" : [ ],
  "formAnswers" : [ ],
  "study" : {
    "id" : "60e8136dc1551b0f813ec8f9",
    "title" : "Study1",
    "description" : "Lorem",
    "numParticipants" : 1,
    "numForms" : 2
  }
}, {
  "id" : "60e8190dc1551b0f813ec8fe",
  "title" : "C",
  "description" : "2",
  "numResponses" : 3,
  "questions" : [ ],
  "formAnswers" : [ ],
  "study" : {
    "id" : "60e818f7c1551b0f813ec8fd",
    "title" : "Study2",
    "description" : "A",
    "numParticipants" : 2,
    "numForms" : 2
  }
} ]